evapyrate.py
evapyrate-1.0.0.dist-info/licenses/LICENSE
evapyrate-1.0.0.dist-info/METADATA
evapyrate-1.0.0.dist-info/WHEEL
evapyrate-1.0.0.dist-info/entry_points.txt
evapyrate-1.0.0.dist-info/top_level.txt
evapyrate-1.0.0.dist-info/RECORD
