Metadata-Version: 2.4
Name: evapyrate
Version: 1.0.0
Summary: A fun bijective text transformer, encoding text into ZWCs.
Home-page: https://github.com/Kreusada/Evapyrate
Author: Kreusada
Author-email: kreusadaprojects@gmail.com
Keywords: bijective,encoding,decoding,string,cipher,transformation,reversible,text,ZWC,zero-width
Classifier: Programming Language :: Python
Classifier: Programming Language :: Python :: 3
Classifier: Programming Language :: Python :: 3.5
Classifier: Programming Language :: Python :: 3.6
Classifier: Programming Language :: Python :: 3.7
Classifier: Programming Language :: Python :: 3.8
Classifier: Programming Language :: Python :: 3.9
Classifier: Programming Language :: Python :: 3.10
Classifier: Programming Language :: Python :: 3.11
Classifier: Programming Language :: Python :: 3.12
Classifier: Programming Language :: Python :: 3.13
Classifier: Programming Language :: Python :: Implementation :: CPython
Classifier: Intended Audience :: Developers
Classifier: License :: OSI Approved :: MIT License
Classifier: Operating System :: OS Independent
Classifier: Topic :: Text Processing
Classifier: Development Status :: 5 - Production/Stable
Requires-Python: >=3.5
License-File: LICENSE
Dynamic: license-file
